thera/__init__.py
thera/thera.py
thera-4.0.1.dist-info/LICENSE
thera-4.0.1.dist-info/METADATA
thera-4.0.1.dist-info/WHEEL
thera-4.0.1.dist-info/entry_points.txt
thera-4.0.1.dist-info/top_level.txt
thera-4.0.1.dist-info/RECORD
