Metadata-Version: 2.1
Name: thera
Version: 4.0.1
Summary: Static site generator
Author-email: Craig Howard <craig@seagrape.us>
Project-URL: Homepage, https://seagrape.us/thera.html
Project-URL: Repository, https://pypi.org/project/thera/
Project-URL: Changelog, https://seagrape.us/thera-history.html
Classifier: Programming Language :: Python :: 3
Classifier: License :: OSI Approved :: MIT License
Classifier: Operating System :: OS Independent
License-File: LICENSE
Requires-Dist: mako
Requires-Dist: markdown
Requires-Dist: pyaml
